ackack/__init__.py
ackack-0.1.0.dist-info/WHEEL
ackack-0.1.0.dist-info/METADATA
ackack-0.1.0.dist-info/RECORD
