Metadata-Version: 2.1
Name: ackack
Version: 0.1.0
Summary: 
Author: David Francos
Author-email: opensource@davidfrancos.net
Requires-Python: >=3.9,<4.0
Classifier: Programming Language :: Python :: 3
Classifier: Programming Language :: Python :: 3.9
Requires-Dist: boto3 (>=1.20.31,<2.0.0)
Requires-Dist: fastapi (>=0.71.0,<0.72.0)
Requires-Dist: requests (>=2.27.1,<3.0.0)
Requires-Dist: uvicorn (>=0.16.0,<0.17.0)
Requires-Dist: weback-unofficial (>=0.3.5,<0.4.0)
